odoo/addons/portal_odoo_debranding/README.rst
odoo/addons/portal_odoo_debranding/__init__.py
odoo/addons/portal_odoo_debranding/__manifest__.py
odoo/addons/portal_odoo_debranding/i18n/it.po
odoo/addons/portal_odoo_debranding/i18n/portal_odoo_debranding.pot
odoo/addons/portal_odoo_debranding/readme/CONTRIBUTORS.md
odoo/addons/portal_odoo_debranding/readme/DESCRIPTION.md
odoo/addons/portal_odoo_debranding/static/description/icon.png
odoo/addons/portal_odoo_debranding/static/description/index.html
odoo/addons/portal_odoo_debranding/tests/__init__.py
odoo/addons/portal_odoo_debranding/tests/test_portal_odoo_debranding.py
odoo/addons/portal_odoo_debranding/views/portal_templates.xml
odoo_addon_portal_odoo_debranding-18.0.1.0.0.3.dist-info/METADATA
odoo_addon_portal_odoo_debranding-18.0.1.0.0.3.dist-info/WHEEL
odoo_addon_portal_odoo_debranding-18.0.1.0.0.3.dist-info/top_level.txt
odoo_addon_portal_odoo_debranding-18.0.1.0.0.3.dist-info/RECORD
