Metadata-Version: 2.1
Name: odoo-addon-portal_odoo_debranding
Version: 18.0.1.0.0.3
Requires-Python: >=3.10
Requires-Dist: odoo==18.0.*
Summary: Remove Odoo Branding from Website
Home-page: https://github.com/OCA/server-brand
License: LGPL-3
Author: TAKOBI, Odoo Community Association (OCA)
Author-email: support@odoo-community.org
Classifier: Programming Language :: Python
Classifier: Framework :: Odoo
Classifier: Framework :: Odoo :: 18.0
Classifier: License :: OSI Approved :: GNU Lesser General Public License v3 (LGPLv3)
Classifier: Development Status :: 4 - Beta
